mkdocs_llmstxt_md/__init__.py
mkdocs_llmstxt_md/config.py
mkdocs_llmstxt_md/plugin.py
mkdocs_llmstxt_md-0.2.0.dist-info/METADATA
mkdocs_llmstxt_md-0.2.0.dist-info/WHEEL
mkdocs_llmstxt_md-0.2.0.dist-info/entry_points.txt
mkdocs_llmstxt_md-0.2.0.dist-info/top_level.txt
mkdocs_llmstxt_md-0.2.0.dist-info/RECORD
