Metadata-Version: 2.4
Name: mkdocs-llmstxt-md
Version: 0.2.0
Summary: MkDocs plugin for LLM-friendly documentation with direct markdown serving
Author-email: Nok Lam Chan <mediumnok@gmail.com>
License: MIT
Project-URL: Homepage, https://github.com/noklam/mkdocs-llmstxt-md
Project-URL: Bug Reports, https://github.com/noklam/mkdocs-llmstxt-md/issues
Project-URL: Source, https://github.com/noklam/mkdocs-llmstxt-md
Keywords: mkdocs,plugin,llm,documentation,markdown,ai
Classifier: Development Status :: 4 - Beta
Classifier: Intended Audience :: Developers
Classifier: License :: OSI Approved :: MIT License
Classifier: Programming Language :: Python :: 3
Classifier: Programming Language :: Python :: 3.9
Classifier: Programming Language :: Python :: 3.10
Classifier: Programming Language :: Python :: 3.11
Classifier: Programming Language :: Python :: 3.12
Classifier: Programming Language :: Python :: 3.13
Classifier: Topic :: Documentation
Classifier: Topic :: Software Development :: Documentation
Requires-Python: >=3.9
Requires-Dist: mkdocs>=1.4.0
Requires-Dist: ruff>=0.12.7
